past_time/__init__.py
past_time-0.3.1.dist-info/LICENSE
past_time-0.3.1.dist-info/METADATA
past_time-0.3.1.dist-info/WHEEL
past_time-0.3.1.dist-info/entry_points.txt
past_time-0.3.1.dist-info/RECORD
