Metadata-Version: 2.1
Name: past-time
Version: 0.3.1
Summary: Visualizer for the days of the year
Home-page: https://github.com/audiusGmbH/audiness
License: MIT
Keywords: time,days,year,past
Author: Fabian Affolter
Author-email: fabian@affolter-engineering.ch
Requires-Python: >=3.10,<4.0
Classifier: Development Status :: 3 - Alpha
Classifier: Environment :: Console
Classifier: Intended Audience :: Developers
Classifier: License :: OSI Approved :: MIT License
Classifier: Operating System :: MacOS :: MacOS X
Classifier: Operating System :: Microsoft :: Windows
Classifier: Operating System :: POSIX
Classifier: Programming Language :: Python :: 3
Classifier: Programming Language :: Python :: 3.10
Classifier: Programming Language :: Python :: 3.11
Classifier: Programming Language :: Python :: 3.12
Classifier: Topic :: Utilities
Requires-Dist: click
Requires-Dist: tqdm
Project-URL: Repository, https://github.com/audiusGmbH/audiness
